webengage_frontend/__init__.py
webengage_frontend/charts.py
webengage_frontend/utils.py
webengage_frontend-0.1.1.dist-info/licenses/LICENSE
webengage_frontend-0.1.1.dist-info/METADATA
webengage_frontend-0.1.1.dist-info/WHEEL
webengage_frontend-0.1.1.dist-info/top_level.txt
webengage_frontend-0.1.1.dist-info/RECORD
