Metadata-Version: 2.4
Name: webengage-frontend
Version: 0.1.1
Summary: A Python package for frontend-related functionality with chart visualization tools
Home-page: https://repo.webengage.com/data-consultancy/data-science-consulting-master-repo
Author: WebEngage
Author-email: WebEngage <support@webengage.com>
License: MIT
Project-URL: Homepage, https://repo.webengage.com/data-consultancy/data-science-consulting-master-repo
Project-URL: Documentation, https://repo.webengage.com/data-consultancy/data-science-consulting-master-repo/-/blob/master/webengage-fe/README.md
Project-URL: Repository, https://repo.webengage.com/data-consultancy/data-science-consulting-master-repo
Project-URL: Issues, https://repo.webengage.com/data-consultancy/data-science-consulting-master-repo/-/issues
Keywords: frontend,webengage,charts,visualization,dataframe,echarts,apache-echarts,pyecharts,html,interactive-charts,pandas,bar-chart,data-visualization,web-charts
Classifier: Development Status :: 3 - Alpha
Classifier: Intended Audience :: Developers
Classifier: License :: OSI Approved :: MIT License
Classifier: Programming Language :: Python :: 3
Classifier: Programming Language :: Python :: 3.8
Classifier: Programming Language :: Python :: 3.9
Classifier: Programming Language :: Python :: 3.10
Classifier: Programming Language :: Python :: 3.11
Classifier: Programming Language :: Python :: 3.12
Classifier: Topic :: Software Development :: Libraries :: Python Modules
Classifier: Topic :: Scientific/Engineering :: Visualization
Requires-Python: >=3.8
License-File: LICENSE
Requires-Dist: pandas>=1.5.0
Requires-Dist: pyecharts>=2.0.0
Requires-Dist: snapshot-selenium>=0.1.11
Provides-Extra: dev
Requires-Dist: pytest>=7.0.0; extra == "dev"
Requires-Dist: pytest-cov>=4.0.0; extra == "dev"
Requires-Dist: black>=23.0.0; extra == "dev"
Requires-Dist: flake8>=6.0.0; extra == "dev"
Requires-Dist: mypy>=1.0.0; extra == "dev"
Dynamic: author
Dynamic: home-page
Dynamic: license-file
Dynamic: requires-python
